shirasu/__init__.py
shirasu/addon/__init__.py
shirasu/addon/addon.py
shirasu/addon/exceptions.py
shirasu/addon/pool.py
shirasu/addon/rule.py
shirasu/addons/__init__.py
shirasu/addons/echo.py
shirasu/addons/help.py
shirasu/addons/manage.py
shirasu/addons/reject_tome.py
shirasu/addons/square.py
shirasu/client/__init__.py
shirasu/client/client.py
shirasu/client/mock.py
shirasu/client/onebot.py
shirasu/config.py
shirasu/di.py
shirasu/event.py
shirasu/logger.py
shirasu/message.py
shirasu/py.typed
shirasu/util/__init__.py
shirasu/util/asyncify.py
shirasu/util/future_table.py
shirasu/util/retry.py
shirasu-1.1.6.dist-info/LICENSE
shirasu-1.1.6.dist-info/METADATA
shirasu-1.1.6.dist-info/WHEEL
shirasu-1.1.6.dist-info/RECORD
