Metadata-Version: 2.1
Name: shirasu
Version: 1.1.6
Summary: A simple bot framework to study the principles, based on OneBot v11.
License: MIT
Author: kifuan
Author-email: kifuan@foxmail.com
Requires-Python: >=3.10,<4.0
Classifier: License :: OSI Approved :: MIT License
Classifier: Programming Language :: Python :: 3
Classifier: Programming Language :: Python :: 3.10
Classifier: Programming Language :: Python :: 3.11
Requires-Dist: loguru (>=0.6.0,<0.7.0)
Requires-Dist: pydantic (>=1.10.4,<2.0.0)
Requires-Dist: pyyaml (>=6.0,<7.0)
Requires-Dist: ujson (>=5.7.0,<6.0.0)
Requires-Dist: websockets (>=10.4,<11.0)
